TelegramContract2vCard/__init__.py
TelegramContract2vCard/main.py
TelegramContract2vCard-1.0.2.dist-info/METADATA
TelegramContract2vCard-1.0.2.dist-info/WHEEL
TelegramContract2vCard-1.0.2.dist-info/top_level.txt
TelegramContract2vCard-1.0.2.dist-info/RECORD
